opseq/__init__.py
opseq/__main__.py
opseq-0.1.2.dist-info/METADATA
opseq-0.1.2.dist-info/WHEEL
opseq-0.1.2.dist-info/top_level.txt
opseq-0.1.2.dist-info/RECORD
